{
  "lockfileVersion": 1,
  "packages": {
    "@prompd.io/api-toolkit@latest": {
      "name": "api-toolkit",
      "version": "latest",
      "resolved_version": "1.0.1",
      "integrity": "",
      "dependencies": {},
      "installed_at": "2025-08-31T23:58:08.905150"
    },
    "@prompd.io/core-patterns@2.0.1": {
      "name": "core-patterns",
      "version": "2.0.1",
      "resolved_version": "2.0.1",
      "integrity": "",
      "dependencies": {},
      "installed_at": "2025-08-31T22:40:13.924363"
    },
    "@prompd.io/core-patterns@latest": {
      "name": "core-patterns",
      "version": "latest",
      "resolved_version": "2.0.1",
      "integrity": "",
      "dependencies": {},
      "installed_at": "2025-08-31T22:39:52.006002"
    },
    "@prompd.io/refactoring@latest": {
      "name": "refactoring",
      "version": "latest",
      "resolved_version": "1.0.0",
      "integrity": "",
      "dependencies": {},
      "installed_at": "2025-08-31T23:58:06.477418"
    },
    "@prompd.io/testing@1.0.1": {
      "name": "testing",
      "version": "1.0.1",
      "resolved_version": "1.0.1",
      "integrity": "",
      "dependencies": {},
      "installed_at": "2025-09-09T20:20:07.819296"
    }
  }
}